MANIFEST.in
README.md
setup.py
r3sponse/.version.py
r3sponse/__init__.py
r3sponse.egg-info/PKG-INFO
r3sponse.egg-info/SOURCES.txt
r3sponse.egg-info/dependency_links.txt
r3sponse.egg-info/not-zip-safe
r3sponse.egg-info/requires.txt
r3sponse.egg-info/top_level.txt
r3sponse/classes/__init__.py
r3sponse/classes/config/__init__.py
r3sponse/classes/exceptions/__init__.py
r3sponse/classes/r3sponse/__init__.py
r3sponse/classes/utils/__init__.py
r3sponse/js/r3sponse.html