Metadata-Version: 1.0
Name: r3sponse
Version: 2.10.4
Summary: Some description.
Home-page: http://github.com/vandenberghinc/r3sponse
Author: Daan van den Bergh
Author-email: vandenberghinc.contact@gmail.com
License: MIT
Platform: UNKNOWN
